{
    "usuarios": [
        {
            "nombre": "Montota",
            "apellido": "apolaa",
            "email": "asdasd@asdasd.asdasd",
            "password": "$2y$10$mWnCv0p94bscIzH3I\/M66.i80VX8.qvM5Df0\/cnCZZ7H4Oic6xD.e",
            "fotoPerfil": "5bddc8c170d11.jpg"
        },
        {
            "nombre": "asdasdasd",
            "apellido": "asdasdasd",
            "email": "nico@digitalhouse.com",
            "password": "$2y$10$26JA.w.WW22\/TgPkkOMWKOJdrftDT1wieTtoJEgmEIkT3\/uSDle4S",
            "fotoPerfil": "5bddc8c170d11.jpg"
        },
        {
            "nombre": "edinson",
            "apellido": "apolinar",
            "email": "edinson@icloud.com",
            "password": "$2y$10$Ik0Db\/jZ0x5i4pMhQnVkt.jO.AWdMEd.4l4pkWFa3F\/noeJowU3i.",
            "fotoPerfil": "5be722823d94b.jpg"
        },
        {
            "nombre": "romina",
            "apellido": "sefsef",
            "email": "esfsef@dsfsd.com",
            "password": "$2y$10$8Q8cUjWIul4O4Q3nZVlWI.YLMRvtChV3gzXadusGHDXl8bDg.K.Hm",
            "fotoPerfil": "5be729d0b9ba9.jpg"
        }
    ]
}